chibi_auth0/__init__.py
chibi_auth0/chibi_auth0.py
chibi_auth0/cli.py
chibi_auth0/urls.py
chibi_auth0-0.1.0.dist-info/AUTHORS.rst
chibi_auth0-0.1.0.dist-info/LICENSE
chibi_auth0-0.1.0.dist-info/METADATA
chibi_auth0-0.1.0.dist-info/WHEEL
chibi_auth0-0.1.0.dist-info/entry_points.txt
chibi_auth0-0.1.0.dist-info/top_level.txt
chibi_auth0-0.1.0.dist-info/RECORD
