Metadata-Version: 2.1
Name: chibi-auth0
Version: 0.1.0
Summary: chibi lib for use auth0 api
Home-page: https://github.com/dem4ply/chibi_auth0
Author: dem4ply
Author-email: dem4ply@gmail.com
License: WTFPL
Keywords: chibi_auth0
Platform: UNKNOWN
Classifier: Development Status :: 2 - Pre-Alpha
Classifier: Intended Audience :: Developers
Classifier: License :: Public Domain
Classifier: Natural Language :: English
Classifier: Programming Language :: Python :: 3.7
Classifier: Programming Language :: Python :: 3.8
License-File: LICENSE
License-File: AUTHORS.rst
Requires-Dist: chibi-requests (>=0.5.0)
